rdbpy/interfaces.py
rdbpy/lib_rocksdb.cpython-313-darwin.so
rdbpy/slice_.pxd
rdbpy/universal_compaction.pxd
rdbpy/iterator.pxd
rdbpy/memtablerep.pxd
rdbpy/merge_operators.py
rdbpy/lib_rocksdb.pyx
rdbpy/db.pxd
rdbpy/status.pxd
rdbpy/__init__.py
rdbpy/comparator.pxd
rdbpy/options.pxd
rdbpy/table_factory.pxd
rdbpy/cache.pxd
rdbpy/snapshot.pxd
rdbpy/env.pxd
rdbpy/slice_transform.pxd
rdbpy/lib_rocksdb.pxd
rdbpy/lib_utils.py
rdbpy/filter_policy.pxd
rdbpy/backup.pxd
rdbpy/errors.py
rdbpy/lib_rocksdb.pyi
rdbpy/transaction.pxd
rdbpy/merge_operator.pxd
rdbpy/logger.pxd
rdbpy/std_memory.pxd
rdbpy/include/rdb_include/memtable_factories.hpp
rdbpy/include/rdb_include/merge_operator_wrapper.hpp
rdbpy/include/rdb_include/write_batch_iter_helper.hpp
rdbpy/include/rdb_include/slice_transform_wrapper.hpp
rdbpy/include/rdb_include/comparator_wrapper.hpp
rdbpy/include/rdb_include/utils.hpp
rdbpy/include/rdb_include/filter_policy_wrapper.hpp
rdbpy/.dylibs/libsnappy.1.2.1.dylib
rdbpy/.dylibs/liblz4.1.9.4.dylib
rdbpy/.dylibs/libbz2.1.0.8.dylib
rdbpy/.dylibs/libz.1.3.1.dylib
rdbpy/.dylibs/libzstd.1.5.6.dylib
rdbpython-0.2.1.dist-info/RECORD
rdbpython-0.2.1.dist-info/WHEEL
rdbpython-0.2.1.dist-info/top_level.txt
rdbpython-0.2.1.dist-info/METADATA
rdbpython-0.2.1.dist-info/licenses/LICENSE.md
