Metadata-Version: 2.4
Name: rdbpython
Version: 0.2.1
Summary: Python bindings for RocksDB with Cython
Author-email: Gor Arakelyan <gorarkln@gmail.com>
Maintainer-email: Gor Arakelyan <gorarkln@gmail.com>
License-Expression: MIT
Project-URL: Homepage, https://github.com/everyabc/rdbpy
Project-URL: Documentation, https://github.com/everyabc/rdbpy#readme
Project-URL: Repository, https://github.com/everyabc/rdbpy
Project-URL: Issues, https://github.com/everyabc/rdbpy/issues
Project-URL: PyPI, https://pypi.org/project/rdbpython/
Keywords: rocksdb,database,key-value,storage,embedded,cython
Classifier: Development Status :: 3 - Alpha
Classifier: Intended Audience :: Developers
Classifier: Operating System :: OS Independent
Classifier: Programming Language :: Python :: 3
Classifier: Programming Language :: Python :: 3.9
Classifier: Programming Language :: Python :: 3.10
Classifier: Programming Language :: Python :: 3.11
Classifier: Programming Language :: Python :: 3.12
Classifier: Programming Language :: Python :: 3.13
Classifier: Programming Language :: Python :: Implementation :: CPython
Classifier: Programming Language :: Cython
Classifier: Topic :: Software Development :: Libraries :: Python Modules
Classifier: Topic :: Database
Requires-Python: >=3.9
License-File: LICENSE.md
Requires-Dist: attrs
Provides-Extra: dev
Requires-Dist: ruff>=0.1.0; extra == "dev"
Requires-Dist: pre-commit>=3.0.0; extra == "dev"
Provides-Extra: test
Requires-Dist: pytest>=7.0.0; extra == "test"
Requires-Dist: pytest-cov>=4.0.0; extra == "test"
Requires-Dist: pytest-xdist>=3.0.0; extra == "test"
Requires-Dist: pytest-timeout>=2.1.0; extra == "test"
Requires-Dist: pytest-benchmark>=4.0.0; extra == "test"
Requires-Dist: hypothesis>=6.0.0; extra == "test"
Provides-Extra: cython
Requires-Dist: Cython>=3.0.0; extra == "cython"
Requires-Dist: setuptools>=68.0; extra == "cython"
Provides-Extra: all
Requires-Dist: rdbpy[cython,dev,test]; extra == "all"
Dynamic: license-file
